sphinx_pybtex_etal_style/__init__.py
sphinx_pybtex_etal_style/py.typed
sphinx_pybtex_etal_style/style.py
sphinx_pybtex_etal_style-0.0.3.dist-info/LICENSE
sphinx_pybtex_etal_style-0.0.3.dist-info/METADATA
sphinx_pybtex_etal_style-0.0.3.dist-info/WHEEL
sphinx_pybtex_etal_style-0.0.3.dist-info/top_level.txt
sphinx_pybtex_etal_style-0.0.3.dist-info/RECORD
