Metadata-Version: 2.1
Name: sphinx-pybtex-etal-style
Version: 0.0.3
Summary: Abbreviate long author lists with et al. in BibTeX bibliographies for Sphinx
Author-email: Common Partial Wave Analysis <compwa-admin@ep1.rub.de>
Maintainer-email: compwa-admin@ep1.rub.de
License: BSD 3-Clause License
Project-URL: Changelog, https://github.com/ComPWA/sphinx-pybtex-etal-style/releases
Project-URL: Documentation, https://github.com/ComPWA/sphinx-pybtex-etal-style/blob/main/README.md
Project-URL: Source, https://github.com/ComPWA/sphinx-pybtex-etal-style
Project-URL: Tracker, https://github.com/ComPWA/sphinx-pybtex-etal-style/issues
Keywords: bibliography,bibtex,sphinx
Classifier: Development Status :: 3 - Alpha
Classifier: Intended Audience :: Developers
Classifier: License :: OSI Approved :: BSD License
Classifier: Natural Language :: English
Classifier: Operating System :: OS Independent
Classifier: Programming Language :: Python :: 3.10
Classifier: Programming Language :: Python :: 3.11
Classifier: Programming Language :: Python :: 3.12
Classifier: Programming Language :: Python :: 3.9
Classifier: Programming Language :: Python
Classifier: Topic :: Documentation
Classifier: Topic :: Utilities
Classifier: Typing :: Typed
Requires-Python: >=3.9
License-File: LICENSE
Requires-Dist: pybtex
